{
  "Alt-/": "lua:comment.comment",
  "Alt-g": "ToggleKeyMenu",
  "AltDown": "SpawnMultiCursorDown",
  "AltLeft": "PreviousSplit",
  "AltRight": "NextSplit",
  "AltUp": "SpawnMultiCursorUp",
  "Ctrl-a": "SelectAll",
  "Ctrl-b": "JumpToMatchingBrace",
  "Ctrl-c": "CopyLine|Copy",
  "Ctrl-d": "DuplicateLine",
  "Ctrl-e": "CommandMode",
  "Ctrl-f": "Find",
  "Ctrl-g": "ToggleHelp",
  "Ctrl-k": "CutLine",
  "Ctrl-l": "command-edit:goto ",
  "Ctrl-n": "FindNext",
  "Ctrl-o": "OpenFile",
  "Ctrl-p": "command:fzf",
  "Ctrl-q": "Quit",
  "Ctrl-r": "NextTab",
  "Ctrl-s": "Save",
  "Ctrl-t": "AddTab",
  "Ctrl-v": "Paste",
  "Ctrl-x": "Cut",
  "Ctrl-y": "Redo",
  "Ctrl-z": "Undo",
  "CtrlEnd": "CursorEnd",
  "CtrlHome": "CursorStart",
  "CtrlUnderscore": "lua:comment.comment",
  "Delete": "Delete",
  "Down": "CursorDown",
  "End": "EndOfLine",
  "Home": "StartOfText",
  "Left": "CursorLeft",
  "PageDown": "CursorPageDown",
  "PageUp": "CursorPageUp",
  "Right": "CursorRight",
  "ShiftDown": "SelectDown",
  "ShiftEnd": "SelectToEndOfLine",
  "ShiftHome": "SelectToStartOfTextToggle",
  "ShiftLeft": "SelectLeft",
  "ShiftRight": "SelectRight",
  "ShiftUp": "SelectUp",
  "Up": "CursorUp"
}
